LICENSE.txt
MANIFEST.in
README.md
setup.py
MimV6/MimV6.py
MimV6/PacketPrinter.py
MimV6/PacketStats.py
MimV6/Sniffer.py
MimV6/Spoofer.py
MimV6/__init__.py
MimV6/test_PacketPrinter.py
MimV6/test_PacketStats.py
MimV6.egg-info/PKG-INFO
MimV6.egg-info/SOURCES.txt
MimV6.egg-info/dependency_links.txt
MimV6.egg-info/entry_points.txt
MimV6.egg-info/requires.txt
MimV6.egg-info/top_level.txt