Metadata-Version: 2.1
Name: MimV6
Version: 1.0.0
Summary: This package implement a Man In the Middle attack in IPv6, a IPv6 Sniffer and a Statistic Packet Tool.
Home-page: https://gitlab.com/ChrisASSR/MimV6/
Author: gitlab.com@ChrisASSR, gitlab.com@tHz_FireStorm, gitlab.com@lecorrem, gitlab.com@mrbouk
Author-email: mauricelambert434@gmail.com
License: UNKNOWN
Platform: UNKNOWN
Classifier: Programming Language :: Python
Classifier: Development Status :: 5 - Production/Stable
Classifier: Environment :: Console
Classifier: Natural Language :: English
Classifier: Operating System :: OS Independent
Classifier: Programming Language :: Python :: 3.8
Requires-Python: >=3.6
